{
  "last_seen": {
    "VahidOnline": 75799,
    "VahidHeadline": 300555,
    "VahidOOnLine": 242861,
    "bbcpersian": 282360,
    "RadioFarda": 157705,
    "IranintlTV": 339676,
    "Tasnimnews": 406620,
    "Farsna": 438725,
    "isna94": 385094,
    "irna_1313": 411138,
    "khabarfouri": 541419,
    "Khabar_Fouri": 527849,
    "akhbarefori": 654734,
    "khabari": 175726,
    "akharinkhabar": 597590,
    "entekhab_ir": 367701,
    "Alarabiya_far": 141923,
    "dw_farsi": 125294,
    "thezoomon": 1788
  }
}