{
  "last_seen": {
    "VahidOnline": 71105,
    "VahidHeadline": 281858,
    "VahidOOnLine": 222131,
    "bbcpersian": 272694,
    "RadioFarda": 153996,
    "IranintlTV": 323397,
    "Tasnimnews": 390591,
    "Farsna": 413851,
    "isna94": 368610,
    "irna_1313": 391772,
    "khabarfouri": 523275,
    "Khabar_Fouri": 488358,
    "akhbarefori": 622182,
    "khabari": 165968,
    "akharinkhabar": 561864,
    "entekhab_ir": 353066,
    "Alarabiya_far": 132351,
    "dw_farsi": 121771,
    "thezoomon": 1676
  }
}