{
  "last_seen": {
    "VahidOnline": 75951,
    "VahidHeadline": 301795,
    "VahidOOnLine": 243821,
    "bbcpersian": 282924,
    "RadioFarda": 157933,
    "IranintlTV": 340687,
    "Tasnimnews": 406620,
    "Farsna": 440098,
    "isna94": 386216,
    "irna_1313": 413378,
    "khabarfouri": 542674,
    "Khabar_Fouri": 528965,
    "akhbarefori": 656408,
    "khabari": 176696,
    "akharinkhabar": 599499,
    "entekhab_ir": 368521,
    "Alarabiya_far": 142438,
    "dw_farsi": 125542,
    "thezoomon": 1985
  }
}