{
  "last_seen": {
    "VahidOnline": 77407,
    "VahidHeadline": 311875,
    "VahidOOnLine": 251606,
    "bbcpersian": 287415,
    "RadioFarda": 159855,
    "IranintlTV": 349109,
    "Tasnimnews": 406620,
    "Farsna": 452043,
    "isna94": 395783,
    "irna_1313": 432640,
    "khabarfouri": 553733,
    "Khabar_Fouri": 539502,
    "akhbarefori": 674333,
    "khabari": 186828,
    "akharinkhabar": 621551,
    "entekhab_ir": 375143,
    "Alarabiya_far": 146269,
    "dw_farsi": 127793,
    "thezoomon": 3527
  }
}