{
  "last_seen": {
    "VahidOnline": 76859,
    "VahidHeadline": 308699,
    "VahidOOnLine": 249108,
    "bbcpersian": 286080,
    "RadioFarda": 159223,
    "IranintlTV": 346540,
    "Tasnimnews": 406620,
    "Farsna": 448491,
    "isna94": 393063,
    "irna_1313": 426945,
    "khabarfouri": 550506,
    "Khabar_Fouri": 535877,
    "akhbarefori": 668718,
    "khabari": 182838,
    "akharinkhabar": 616565,
    "entekhab_ir": 373145,
    "Alarabiya_far": 145145,
    "dw_farsi": 127059,
    "thezoomon": 3100
  }
}