{
  "last_seen": {
    "VahidOnline": 74788,
    "VahidHeadline": 291968,
    "VahidOOnLine": 233457,
    "bbcpersian": 278053,
    "RadioFarda": 156017,
    "IranintlTV": 331810,
    "Tasnimnews": 406620,
    "Farsna": 428968,
    "isna94": 377370,
    "irna_1313": 399611,
    "khabarfouri": 534061,
    "Khabar_Fouri": 518149,
    "akhbarefori": 646707,
    "khabari": 171883,
    "akharinkhabar": 583707,
    "entekhab_ir": 361364,
    "Alarabiya_far": 138306,
    "dw_farsi": 123525,
    "thezoomon": 1676
  }
}