{
  "last_seen": {
    "VahidOnline": 75524,
    "VahidHeadline": 298435,
    "VahidOOnLine": 240709,
    "bbcpersian": 281330,
    "RadioFarda": 157294,
    "IranintlTV": 337701,
    "Tasnimnews": 406620,
    "Farsna": 436289,
    "isna94": 383027,
    "irna_1313": 407657,
    "khabarfouri": 539437,
    "Khabar_Fouri": 525638,
    "akhbarefori": 652742,
    "khabari": 174758,
    "akharinkhabar": 594059,
    "entekhab_ir": 366141,
    "Alarabiya_far": 140978,
    "dw_farsi": 124810,
    "thezoomon": 1676
  }
}