{
  "last_seen": {
    "VahidOnline": 74872,
    "VahidHeadline": 293061,
    "VahidOOnLine": 234797,
    "bbcpersian": 278624,
    "RadioFarda": 156227,
    "IranintlTV": 332857,
    "Tasnimnews": 406620,
    "Farsna": 430172,
    "isna94": 378322,
    "irna_1313": 400626,
    "khabarfouri": 535012,
    "Khabar_Fouri": 519781,
    "akhbarefori": 647964,
    "khabari": 172513,
    "akharinkhabar": 585563,
    "entekhab_ir": 362236,
    "Alarabiya_far": 138746,
    "dw_farsi": 123795,
    "thezoomon": 1676
  }
}