{
  "last_seen": {
    "VahidOnline": 72680,
    "VahidHeadline": 285863,
    "VahidOOnLine": 225999,
    "bbcpersian": 274666,
    "RadioFarda": 154770,
    "IranintlTV": 326282,
    "Tasnimnews": 397342,
    "Farsna": 420401,
    "isna94": 372320,
    "irna_1313": 394944,
    "khabarfouri": 528177,
    "Khabar_Fouri": 501279,
    "akhbarefori": 636301,
    "khabari": 167844,
    "akharinkhabar": 571039,
    "entekhab_ir": 356416,
    "Alarabiya_far": 134710,
    "dw_farsi": 122444,
    "thezoomon": 1676
  }
}