{
  "last_seen": {
    "VahidOnline": 76951,
    "VahidHeadline": 309440,
    "VahidOOnLine": 249666,
    "bbcpersian": 286423,
    "RadioFarda": 159374,
    "IranintlTV": 347125,
    "Tasnimnews": 406620,
    "Farsna": 449379,
    "isna94": 393710,
    "irna_1313": 428303,
    "khabarfouri": 551337,
    "Khabar_Fouri": 536624,
    "akhbarefori": 670120,
    "khabari": 183692,
    "akharinkhabar": 618002,
    "entekhab_ir": 373604,
    "Alarabiya_far": 145391,
    "dw_farsi": 127207,
    "thezoomon": 3217
  }
}