{
  "last_seen": {
    "VahidOnline": 75000,
    "VahidHeadline": 294201,
    "VahidOOnLine": 236148,
    "bbcpersian": 279204,
    "RadioFarda": 156456,
    "IranintlTV": 333949,
    "Tasnimnews": 406620,
    "Farsna": 431498,
    "isna94": 379245,
    "irna_1313": 401837,
    "khabarfouri": 535964,
    "Khabar_Fouri": 521266,
    "akhbarefori": 649113,
    "khabari": 173024,
    "akharinkhabar": 587350,
    "entekhab_ir": 363125,
    "Alarabiya_far": 139255,
    "dw_farsi": 123986,
    "thezoomon": 1676
  }
}