{
  "last_seen": {
    "VahidOnline": 75621,
    "VahidHeadline": 299306,
    "VahidOOnLine": 241557,
    "bbcpersian": 281799,
    "RadioFarda": 157458,
    "IranintlTV": 338454,
    "Tasnimnews": 406620,
    "Farsna": 437255,
    "isna94": 383827,
    "irna_1313": 409017,
    "khabarfouri": 540220,
    "Khabar_Fouri": 526519,
    "akhbarefori": 653530,
    "khabari": 175014,
    "akharinkhabar": 595412,
    "entekhab_ir": 366763,
    "Alarabiya_far": 141359,
    "dw_farsi": 125017,
    "thezoomon": 1676
  }
}