{
  "last_seen": {
    "VahidOnline": 73343,
    "VahidHeadline": 288225,
    "VahidOOnLine": 228382,
    "bbcpersian": 275952,
    "RadioFarda": 155246,
    "IranintlTV": 328193,
    "Tasnimnews": 401409,
    "Farsna": 423987,
    "isna94": 373845,
    "irna_1313": 396208,
    "khabarfouri": 530358,
    "Khabar_Fouri": 508795,
    "akhbarefori": 640287,
    "khabari": 169045,
    "akharinkhabar": 575902,
    "entekhab_ir": 357393,
    "Alarabiya_far": 136166,
    "dw_farsi": 122856,
    "thezoomon": 1676
  }
}