{
  "last_seen": {
    "VahidOnline": 73202,
    "VahidHeadline": 287777,
    "VahidOOnLine": 227821,
    "bbcpersian": 275722,
    "RadioFarda": 155143,
    "IranintlTV": 327743,
    "Tasnimnews": 400452,
    "Farsna": 423306,
    "isna94": 373474,
    "irna_1313": 395882,
    "khabarfouri": 529931,
    "Khabar_Fouri": 507152,
    "akhbarefori": 639332,
    "khabari": 168736,
    "akharinkhabar": 574852,
    "entekhab_ir": 356996,
    "Alarabiya_far": 135856,
    "dw_farsi": 122755,
    "thezoomon": 1676
  }
}