{
  "last_seen": {
    "VahidOnline": 76781,
    "VahidHeadline": 307811,
    "VahidOOnLine": 248508,
    "bbcpersian": 285687,
    "RadioFarda": 159070,
    "IranintlTV": 345720,
    "Tasnimnews": 406620,
    "Farsna": 446654,
    "isna94": 391863,
    "irna_1313": 424864,
    "khabarfouri": 549053,
    "Khabar_Fouri": 534845,
    "akhbarefori": 666370,
    "khabari": 181853,
    "akharinkhabar": 613910,
    "entekhab_ir": 372496,
    "Alarabiya_far": 144814,
    "dw_farsi": 126844,
    "thezoomon": 2937
  }
}