{
  "last_seen": {
    "VahidOnline": 75454,
    "VahidHeadline": 297729,
    "VahidOOnLine": 240015,
    "bbcpersian": 280972,
    "RadioFarda": 157154,
    "IranintlTV": 337092,
    "Tasnimnews": 406620,
    "Farsna": 435511,
    "isna94": 382367,
    "irna_1313": 406635,
    "khabarfouri": 538845,
    "Khabar_Fouri": 524985,
    "akhbarefori": 652215,
    "khabari": 174468,
    "akharinkhabar": 592986,
    "entekhab_ir": 365634,
    "Alarabiya_far": 140684,
    "dw_farsi": 124671,
    "thezoomon": 1676
  }
}