{
  "last_seen": {
    "VahidOnline": 76435,
    "VahidHeadline": 304370,
    "VahidOOnLine": 245940,
    "bbcpersian": 284068,
    "RadioFarda": 158406,
    "IranintlTV": 342769,
    "Tasnimnews": 406620,
    "Farsna": 442666,
    "isna94": 388301,
    "irna_1313": 417802,
    "khabarfouri": 545271,
    "Khabar_Fouri": 531626,
    "akhbarefori": 660258,
    "khabari": 179092,
    "akharinkhabar": 604440,
    "entekhab_ir": 370400,
    "Alarabiya_far": 143476,
    "dw_farsi": 126078,
    "thezoomon": 2376
  }
}