{
  "last_seen": {
    "VahidOnline": 76810,
    "VahidHeadline": 308464,
    "VahidOOnLine": 248908,
    "bbcpersian": 285970,
    "RadioFarda": 159178,
    "IranintlTV": 346359,
    "Tasnimnews": 406620,
    "Farsna": 448076,
    "isna94": 392791,
    "irna_1313": 426454,
    "khabarfouri": 550173,
    "Khabar_Fouri": 535472,
    "akhbarefori": 668120,
    "khabari": 182506,
    "akharinkhabar": 616086,
    "entekhab_ir": 372957,
    "Alarabiya_far": 145056,
    "dw_farsi": 127010,
    "thezoomon": 3051
  }
}