{
  "last_seen": {
    "VahidOnline": 73109,
    "VahidHeadline": 287470,
    "VahidOOnLine": 227528,
    "bbcpersian": 275556,
    "RadioFarda": 155067,
    "IranintlTV": 327492,
    "Tasnimnews": 399983,
    "Farsna": 422942,
    "isna94": 373225,
    "irna_1313": 395681,
    "khabarfouri": 529692,
    "Khabar_Fouri": 506355,
    "akhbarefori": 638780,
    "khabari": 168543,
    "akharinkhabar": 574203,
    "entekhab_ir": 356788,
    "Alarabiya_far": 135645,
    "dw_farsi": 122704,
    "thezoomon": 1676
  }
}