{
  "last_seen": {
    "VahidOnline": 73388,
    "VahidHeadline": 288424,
    "VahidOOnLine": 228642,
    "bbcpersian": 276068,
    "RadioFarda": 155271,
    "IranintlTV": 328378,
    "Tasnimnews": 401724,
    "Farsna": 424220,
    "isna94": 373996,
    "irna_1313": 396343,
    "khabarfouri": 530574,
    "Khabar_Fouri": 509257,
    "akhbarefori": 640646,
    "khabari": 169181,
    "akharinkhabar": 576284,
    "entekhab_ir": 357538,
    "Alarabiya_far": 136272,
    "dw_farsi": 122884,
    "thezoomon": 1676
  }
}