{
  "last_seen": {
    "VahidOnline": 75739,
    "VahidHeadline": 300004,
    "VahidOOnLine": 242352,
    "bbcpersian": 282130,
    "RadioFarda": 157588,
    "IranintlTV": 339161,
    "Tasnimnews": 406620,
    "Farsna": 438241,
    "isna94": 384616,
    "irna_1313": 410459,
    "khabarfouri": 540950,
    "Khabar_Fouri": 527438,
    "akhbarefori": 654252,
    "khabari": 175320,
    "akharinkhabar": 596772,
    "entekhab_ir": 367386,
    "Alarabiya_far": 141673,
    "dw_farsi": 125172,
    "thezoomon": 1676
  }
}