{
  "last_seen": {
    "VahidOnline": 75507,
    "VahidHeadline": 298301,
    "VahidOOnLine": 240566,
    "bbcpersian": 281270,
    "RadioFarda": 157276,
    "IranintlTV": 337567,
    "Tasnimnews": 406620,
    "Farsna": 436074,
    "isna94": 382872,
    "irna_1313": 407433,
    "khabarfouri": 539328,
    "Khabar_Fouri": 525494,
    "akhbarefori": 652606,
    "khabari": 174699,
    "akharinkhabar": 593841,
    "entekhab_ir": 366047,
    "Alarabiya_far": 140906,
    "dw_farsi": 124780,
    "thezoomon": 1676
  }
}