{
  "last_seen": {
    "VahidOnline": 75584,
    "VahidHeadline": 299015,
    "VahidOOnLine": 241233,
    "bbcpersian": 281644,
    "RadioFarda": 157404,
    "IranintlTV": 338156,
    "Tasnimnews": 406620,
    "Farsna": 436979,
    "isna94": 383584,
    "irna_1313": 408617,
    "khabarfouri": 539971,
    "Khabar_Fouri": 526257,
    "akhbarefori": 653325,
    "khabari": 174936,
    "akharinkhabar": 595017,
    "entekhab_ir": 366572,
    "Alarabiya_far": 141229,
    "dw_farsi": 124942,
    "thezoomon": 1676
  }
}