{
  "last_seen": {
    "VahidOnline": 75055,
    "VahidHeadline": 294605,
    "VahidOOnLine": 236606,
    "bbcpersian": 279474,
    "RadioFarda": 156523,
    "IranintlTV": 334348,
    "Tasnimnews": 406620,
    "Farsna": 432030,
    "isna94": 379589,
    "irna_1313": 402372,
    "khabarfouri": 536331,
    "Khabar_Fouri": 521761,
    "akhbarefori": 649524,
    "khabari": 173209,
    "akharinkhabar": 588084,
    "entekhab_ir": 363434,
    "Alarabiya_far": 139415,
    "dw_farsi": 124058,
    "thezoomon": 1676
  }
}