{
  "last_seen": {
    "VahidOnline": 74664,
    "VahidHeadline": 290991,
    "VahidOOnLine": 232117,
    "bbcpersian": 277489,
    "RadioFarda": 155823,
    "IranintlTV": 330846,
    "Tasnimnews": 406376,
    "Farsna": 427828,
    "isna94": 376472,
    "irna_1313": 398796,
    "khabarfouri": 532996,
    "Khabar_Fouri": 516432,
    "akhbarefori": 645626,
    "khabari": 171211,
    "akharinkhabar": 582042,
    "entekhab_ir": 360419,
    "Alarabiya_far": 137868,
    "dw_farsi": 123335,
    "thezoomon": 1676
  }
}