{
  "last_seen": {
    "VahidOnline": 74981,
    "VahidHeadline": 293979,
    "VahidOOnLine": 235873,
    "bbcpersian": 279082,
    "RadioFarda": 156421,
    "IranintlTV": 333703,
    "Tasnimnews": 406620,
    "Farsna": 431232,
    "isna94": 379060,
    "irna_1313": 401589,
    "khabarfouri": 535786,
    "Khabar_Fouri": 520983,
    "akhbarefori": 648886,
    "khabari": 172893,
    "akharinkhabar": 586987,
    "entekhab_ir": 362961,
    "Alarabiya_far": 139176,
    "dw_farsi": 123955,
    "thezoomon": 1676
  }
}