{
  "last_seen": {
    "VahidOnline": 74397,
    "VahidHeadline": 290350,
    "VahidOOnLine": 231247,
    "bbcpersian": 277162,
    "RadioFarda": 155674,
    "IranintlTV": 330231,
    "Tasnimnews": 405436,
    "Farsna": 426986,
    "isna94": 375837,
    "irna_1313": 398200,
    "khabarfouri": 532472,
    "Khabar_Fouri": 514984,
    "akhbarefori": 644545,
    "khabari": 170636,
    "akharinkhabar": 580637,
    "entekhab_ir": 359687,
    "Alarabiya_far": 137436,
    "dw_farsi": 123238,
    "thezoomon": 1676
  }
}