{
  "last_seen": {
    "VahidOnline": 73526,
    "VahidHeadline": 288638,
    "VahidOOnLine": 228943,
    "bbcpersian": 276166,
    "RadioFarda": 155321,
    "IranintlTV": 328587,
    "Tasnimnews": 402038,
    "Farsna": 424486,
    "isna94": 374211,
    "irna_1313": 396516,
    "khabarfouri": 530814,
    "Khabar_Fouri": 509906,
    "akhbarefori": 641165,
    "khabari": 169330,
    "akharinkhabar": 576775,
    "entekhab_ir": 357740,
    "Alarabiya_far": 136402,
    "dw_farsi": 122924,
    "thezoomon": 1676
  }
}