{
  "last_seen": {
    "VahidOnline": 75080,
    "VahidHeadline": 294952,
    "VahidOOnLine": 236892,
    "bbcpersian": 279612,
    "RadioFarda": 156620,
    "IranintlTV": 334583,
    "Tasnimnews": 406620,
    "Farsna": 432343,
    "isna94": 379838,
    "irna_1313": 402688,
    "khabarfouri": 536521,
    "Khabar_Fouri": 522059,
    "akhbarefori": 649808,
    "khabari": 173288,
    "akharinkhabar": 588601,
    "entekhab_ir": 363612,
    "Alarabiya_far": 139524,
    "dw_farsi": 124127,
    "thezoomon": 1676
  }
}