{
  "last_seen": {
    "VahidOnline": 74642,
    "VahidHeadline": 290848,
    "VahidOOnLine": 231933,
    "bbcpersian": 277416,
    "RadioFarda": 155801,
    "IranintlTV": 330687,
    "Tasnimnews": 406171,
    "Farsna": 427622,
    "isna94": 376323,
    "irna_1313": 398646,
    "khabarfouri": 532870,
    "Khabar_Fouri": 516201,
    "akhbarefori": 645450,
    "khabari": 171118,
    "akharinkhabar": 581744,
    "entekhab_ir": 360293,
    "Alarabiya_far": 137819,
    "dw_farsi": 123322,
    "thezoomon": 1676
  }
}