{
  "last_seen": {
    "VahidOnline": 76459,
    "VahidHeadline": 304599,
    "VahidOOnLine": 246105,
    "bbcpersian": 284193,
    "RadioFarda": 158445,
    "IranintlTV": 342936,
    "Tasnimnews": 406620,
    "Farsna": 442979,
    "isna94": 388540,
    "irna_1313": 418287,
    "khabarfouri": 545523,
    "Khabar_Fouri": 531919,
    "akhbarefori": 660679,
    "khabari": 179240,
    "akharinkhabar": 605091,
    "entekhab_ir": 370522,
    "Alarabiya_far": 143548,
    "dw_farsi": 126119,
    "thezoomon": 2408
  }
}