{
  "last_seen": {
    "VahidOnline": 77188,
    "VahidHeadline": 310637,
    "VahidOOnLine": 250618,
    "bbcpersian": 286898,
    "RadioFarda": 159615,
    "IranintlTV": 348073,
    "Tasnimnews": 406620,
    "Farsna": 450648,
    "isna94": 394693,
    "irna_1313": 430291,
    "khabarfouri": 552475,
    "Khabar_Fouri": 538038,
    "akhbarefori": 672157,
    "khabari": 185239,
    "akharinkhabar": 619656,
    "entekhab_ir": 374402,
    "Alarabiya_far": 145826,
    "dw_farsi": 127503,
    "thezoomon": 3392
  }
}