{
  "last_seen": {
    "VahidOnline": 73033,
    "VahidHeadline": 287294,
    "VahidOOnLine": 227294,
    "bbcpersian": 275447,
    "RadioFarda": 155037,
    "IranintlTV": 327313,
    "Tasnimnews": 399590,
    "Farsna": 422552,
    "isna94": 373052,
    "irna_1313": 395535,
    "khabarfouri": 529430,
    "Khabar_Fouri": 505417,
    "akhbarefori": 638158,
    "khabari": 168395,
    "akharinkhabar": 573659,
    "entekhab_ir": 356621,
    "Alarabiya_far": 135538,
    "dw_farsi": 122671,
    "thezoomon": 1676
  }
}