{
  "last_seen": {
    "VahidOnline": 76522,
    "VahidHeadline": 305005,
    "VahidOOnLine": 246409,
    "bbcpersian": 284403,
    "RadioFarda": 158512,
    "IranintlTV": 343248,
    "Tasnimnews": 406620,
    "Farsna": 443258,
    "isna94": 388822,
    "irna_1313": 418793,
    "khabarfouri": 545838,
    "Khabar_Fouri": 532191,
    "akhbarefori": 661157,
    "khabari": 179491,
    "akharinkhabar": 605969,
    "entekhab_ir": 370703,
    "Alarabiya_far": 143701,
    "dw_farsi": 126189,
    "thezoomon": 2450
  }
}