{
  "last_seen": {
    "VahidOnline": 72129,
    "VahidHeadline": 283942,
    "VahidOOnLine": 224217,
    "bbcpersian": 273710,
    "RadioFarda": 154411,
    "IranintlTV": 324886,
    "Tasnimnews": 394186,
    "Farsna": 416954,
    "isna94": 370465,
    "irna_1313": 393568,
    "khabarfouri": 526119,
    "Khabar_Fouri": 495731,
    "akhbarefori": 629694,
    "khabari": 166441,
    "akharinkhabar": 566622,
    "entekhab_ir": 354927,
    "Alarabiya_far": 133698,
    "dw_farsi": 122156,
    "thezoomon": 1676
  }
}