{
  "last_seen": {
    "VahidOnline": 74233,
    "VahidHeadline": 290090,
    "VahidOOnLine": 230885,
    "bbcpersian": 277014,
    "RadioFarda": 155624,
    "IranintlTV": 329980,
    "Tasnimnews": 404862,
    "Farsna": 426606,
    "isna94": 375564,
    "irna_1313": 397908,
    "khabarfouri": 532247,
    "Khabar_Fouri": 514184,
    "akhbarefori": 643958,
    "khabari": 170485,
    "akharinkhabar": 579886,
    "entekhab_ir": 359358,
    "Alarabiya_far": 137281,
    "dw_farsi": 123179,
    "thezoomon": 1676
  }
}